debug_node_api/README.md
debug_node_api/__init__.py
debug_node_api/debug_node_api_client.py
debug_node_api/debug_node_api_description.py
debug_node_api/py.typed
hiveio_debug_node_api-1.28.4.dist-info/METADATA
hiveio_debug_node_api-1.28.4.dist-info/WHEEL
hiveio_debug_node_api-1.28.4.dist-info/RECORD
