Metadata-Version: 2.4
Name: hiveio-debug-node-api
Version: 1.28.4
Summary: 
Requires-Python: >=3.12,<4.0
Classifier: Programming Language :: Python :: 3
Classifier: Programming Language :: Python :: 3.12
Classifier: Programming Language :: Python :: 3.13
Classifier: Programming Language :: Python :: 3.14
Requires-Dist: hiveio-beekeepy (==1.28.0)
